{
  "mcpServers": {
    "overmind": {
      "transport": "http-stream",
      "url": "http://localhost:3099",
      "description": "OverMind-MCP principal - 14 outils (run_agent, create_agent, memory, etc.)"
    },
    "memory": {
      "transport": "http-stream",
      "url": "http://localhost:3099",
      "description": "OverMind-MCP mémoire only - 3 outils (memory_search, memory_store, memory_runs)"
    },
"postgresql": {
      "transport": "http-stream",
      "url": "http://localhost:5433",
      "description": "PostgreSQL MCP - Base de données vectorielle"
    }
  },
  "description": "Configuration MCP OverMind-MCP optimisée pour installation globale npm avec support HTTP",
  "version": "2.3.0",
  "installation": "npm install -g overmind-mcp",
  "note": "Les serveurs HTTP doivent être lancés avant utilisation. Voir bin/README.md pour les commandes de démarrage."
}